pylogue/__init__.py
pylogue/__pre_init__.py
pylogue/_modidx.py
pylogue/cards.py
pylogue/chat.py
pylogue/chatapp.py
pylogue/health.py
pylogue/renderer.py
pylogue/service.py
pylogue/session.py
pylogue-0.3.dist-info/licenses/AUTHORS.md
pylogue-0.3.dist-info/licenses/LICENSE
pylogue-0.3.dist-info/METADATA
pylogue-0.3.dist-info/WHEEL
pylogue-0.3.dist-info/entry_points.txt
pylogue-0.3.dist-info/top_level.txt
pylogue-0.3.dist-info/RECORD
